featureflags/__init__.py
featureflags/analytics.py
featureflags/api.py
featureflags/client.py
featureflags/config.py
featureflags/interface.py
featureflags/lru_cache.py
featureflags/persisting.py
featureflags/polling.py
featureflags/repository.py
featureflags/sdk_logging_codes.py
featureflags/sse_client.py
featureflags/streaming.py
featureflags/util.py
featureflags/dto/__init__.py
featureflags/dto/message.py
featureflags/evaluations/__init__.py
featureflags/evaluations/auth_target.py
featureflags/evaluations/constants.py
featureflags/evaluations/evaluator.py
featureflags/evaluations/strategy.py
featureflags/ftypes/__init__.py
featureflags/ftypes/boolean.py
featureflags/ftypes/integer.py
featureflags/ftypes/interface.py
featureflags/ftypes/json.py
featureflags/ftypes/number.py
featureflags/ftypes/string.py
featureflags/ftypes/utils.py
featureflags/openapi/__init__.py
featureflags/openapi/config/__init__.py
featureflags/openapi/config/client.py
featureflags/openapi/config/errors.py
featureflags/openapi/config/types.py
featureflags/openapi/config/api/__init__.py
featureflags/openapi/config/api/client/__init__.py
featureflags/openapi/config/api/client/authenticate.py
featureflags/openapi/config/api/client/get_all_segments.py
featureflags/openapi/config/api/client/get_evaluation_by_identifier.py
featureflags/openapi/config/api/client/get_evaluations.py
featureflags/openapi/config/api/client/get_feature_config.py
featureflags/openapi/config/api/client/get_feature_config_by_identifier.py
featureflags/openapi/config/api/client/get_segment_by_identifier.py
featureflags/openapi/config/api/client/stream.py
featureflags/openapi/config/api/metrics/__init__.py
featureflags/openapi/config/api/metrics/post_metrics.py
featureflags/openapi/config/api/proxy/__init__.py
featureflags/openapi/config/api/proxy/authenticate_proxy_key.py
featureflags/openapi/config/api/proxy/get_proxy_config.py
featureflags/openapi/config/models/__init__.py
harness_featureflags-1.7.3.dist-info/AUTHORS.rst
harness_featureflags-1.7.3.dist-info/LICENSE
harness_featureflags-1.7.3.dist-info/METADATA
harness_featureflags-1.7.3.dist-info/WHEEL
harness_featureflags-1.7.3.dist-info/top_level.txt
harness_featureflags-1.7.3.dist-info/RECORD
