Metadata-Version: 2.1
Name: harness-featureflags
Version: 1.7.3
Summary: Feature flag server SDK for python
Home-page: https://github.com/harness/ff-python-server-sdk
Author: Harness
Author-email: support@harness.io
License: Apache Software License 2.0
Keywords: featureflags
Classifier: Development Status :: 2 - Pre-Alpha
Classifier: Intended Audience :: Developers
Classifier: License :: OSI Approved :: Apache Software License
Classifier: Natural Language :: English
Classifier: Programming Language :: Python :: 3
Classifier: Programming Language :: Python :: 3.5
Classifier: Programming Language :: Python :: 3.6
Classifier: Programming Language :: Python :: 3.7
Classifier: Programming Language :: Python :: 3.8
Requires-Python: >=3.5
License-File: LICENSE
License-File: AUTHORS.rst
Requires-Dist: httpx (>=0.24.1)
Requires-Dist: pyjwt (>=2.4.0)
Requires-Dist: attrs (>=23.2.0)
Requires-Dist: mmh3 (>=3.0.0)
Requires-Dist: requests (>=2.31.0)
Requires-Dist: tenacity (>=8.2.0)
Requires-Dist: typing-extensions (>=4.7.1)
